LICENSE.txt
MANIFEST.in
README.rst
release-history.rst
requirements.txt
setup.py
cazipcode/__init__.py
cazipcode/search.py
cazipcode/zzz_manual_install.py
cazipcode.egg-info/PKG-INFO
cazipcode.egg-info/SOURCES.txt
cazipcode.egg-info/dependency_links.txt
cazipcode.egg-info/requires.txt
cazipcode.egg-info/top_level.txt
cazipcode/__pycache__/__init__.cpython-34.pyc
cazipcode/__pycache__/search.cpython-34.pyc
cazipcode/data/__init__.py
cazipcode/data/canada_postalcode.json.gz
cazipcode/data/__pycache__/__init__.cpython-34.pyc
cazipcode/pkg/__init__.py
cazipcode/pkg/geo_search.py
cazipcode/pkg/nameddict.py
cazipcode/pkg/six.py
cazipcode/pkg/__pycache__/__init__.cpython-34.pyc
cazipcode/pkg/__pycache__/geo_search.cpython-34.pyc
cazipcode/pkg/__pycache__/nameddict.cpython-34.pyc
cazipcode/pkg/__pycache__/six.cpython-34.pyc
cazipcode/pkg/fuzzywuzzy/StringMatcher.py
cazipcode/pkg/fuzzywuzzy/__init__.py
cazipcode/pkg/fuzzywuzzy/fuzz.py
cazipcode/pkg/fuzzywuzzy/process.py
cazipcode/pkg/fuzzywuzzy/string_processing.py
cazipcode/pkg/fuzzywuzzy/utils.py
cazipcode/pkg/fuzzywuzzy/__pycache__/StringMatcher.cpython-34.pyc
cazipcode/pkg/fuzzywuzzy/__pycache__/__init__.cpython-34.pyc
cazipcode/pkg/fuzzywuzzy/__pycache__/fuzz.cpython-34.pyc
cazipcode/pkg/fuzzywuzzy/__pycache__/process.cpython-34.pyc
cazipcode/pkg/fuzzywuzzy/__pycache__/string_processing.cpython-34.pyc
cazipcode/pkg/fuzzywuzzy/__pycache__/utils.cpython-34.pyc
cazipcode/pkg/superjson/__init__.py
cazipcode/pkg/superjson/_superjson.py
cazipcode/pkg/superjson/comments.py
cazipcode/pkg/superjson/compresslib.py
cazipcode/pkg/superjson/util.py
cazipcode/pkg/superjson/warning.py
cazipcode/pkg/superjson/zzz_manual_install.py
cazipcode/pkg/superjson/__pycache__/__init__.cpython-34.pyc
cazipcode/pkg/superjson/__pycache__/_superjson.cpython-34.pyc
cazipcode/pkg/superjson/__pycache__/comments.cpython-34.pyc
cazipcode/pkg/superjson/__pycache__/compresslib.cpython-34.pyc
cazipcode/pkg/superjson/__pycache__/util.cpython-34.pyc
cazipcode/pkg/superjson/__pycache__/warning.cpython-34.pyc
cazipcode/pkg/superjson/pkg/__init__.py
cazipcode/pkg/superjson/pkg/six.py
